py_pol/__init__.py
py_pol/drawings.py
py_pol/jones_matrix.py
py_pol/jones_vector.py
py_pol/mueller.py
py_pol/py_pol.py
py_pol/stokes.py
py_pol/utils.py
py_pol-1.1.3.dist-info/AUTHORS.rst
py_pol-1.1.3.dist-info/LICENSE
py_pol-1.1.3.dist-info/METADATA
py_pol-1.1.3.dist-info/WHEEL
py_pol-1.1.3.dist-info/entry_points.txt
py_pol-1.1.3.dist-info/top_level.txt
py_pol-1.1.3.dist-info/RECORD
