Metadata-Version: 2.1
Name: py_pol
Version: 1.1.3
Summary: Jones and Mueller polarization - Optics
Home-page: https://bitbucket.org/optbrea/py_pol/src/master/
Author: Jesus del Hoyo Munoz / Luis Miguel Sanchez Brea
Author-email: optbrea@ucm.es
License: MIT license
Keywords: py_pol,optics,polarization,Jones,Stokes,Mueller
Classifier: Development Status :: 4 - Beta
Classifier: Intended Audience :: Science/Research
Classifier: License :: OSI Approved :: MIT License
Classifier: Natural Language :: English
Classifier: Programming Language :: Python :: 3
Classifier: Programming Language :: Python :: 3.6
Classifier: Programming Language :: Python :: 3.7
Classifier: Programming Language :: Python :: 3.8
Classifier: Programming Language :: Python :: 3.9
Classifier: Programming Language :: Python :: 3.10
License-File: LICENSE
License-File: AUTHORS.rst
